tupac/__init__.py
tupac/cli.py
tupac/py.typed
tupac-0.1.0.dist-info/METADATA
tupac-0.1.0.dist-info/WHEEL
tupac-0.1.0.dist-info/entry_points.txt
tupac-0.1.0.dist-info/licenses/LICENSE
tupac-0.1.0.dist-info/RECORD
