Metadata-Version: 2.4
Name: tupac
Version: 0.1.0
Summary: A GPT wrapper CLI with proper MCP tool & resource support
Author-email: Tim Kellogg <timothy.kellogg@gmail.com>
License-File: LICENSE
Requires-Python: >=3.12
Requires-Dist: fastmcp>=2.7.0
Requires-Dist: openai>=1.84.0
Requires-Dist: python-dotenv>=1.1.0
Requires-Dist: rich>=14.0.0
Requires-Dist: typer>=0.16.0
